assistant_ostap/__init__.py
assistant_ostap/main.py
assistant_ostap/assistant_ostap/__init__.py
assistant_ostap/assistant_ostap/classes.py
assistant_ostap/assistant_ostap/clean.py
assistant_ostap/assistant_ostap/handlers.py
assistant_ostap/assistant_ostap/notes.py
assistant_ostap-0.0.23.dist-info/LICENSE
assistant_ostap-0.0.23.dist-info/METADATA
assistant_ostap-0.0.23.dist-info/WHEEL
assistant_ostap-0.0.23.dist-info/entry_points.txt
assistant_ostap-0.0.23.dist-info/top_level.txt
assistant_ostap-0.0.23.dist-info/RECORD
