Metadata-Version: 2.1
Name: assistant-ostap
Version: 0.0.23
Summary: Your personal assistant Ostap
Home-page: https://github.com/NeverInMind/Project_Team3/
Author: GoIt Team 3
Author-email: 
Classifier: Programming Language :: Python :: 3.8
Classifier: License :: OSI Approved :: MIT License
Classifier: Operating System :: OS Independent
Requires-Python: >=3.6
License-File: LICENSE
Requires-Dist: fuzzywuzzy ==0.18.0
Requires-Dist: Levenshtein ==0.21.1
Requires-Dist: pyreadline3 ==3.4.1
Requires-Dist: python-Levenshtein ==0.21.1
Requires-Dist: rapidfuzz ==3.1.1
Requires-Dist: rich ==13.5.2
